odoo_scaffolder/__init__.py
odoo_scaffolder/__main__.py
odoo_scaffolder/icons/Accounting.png
odoo_scaffolder/icons/Base.png
odoo_scaffolder/icons/HR.png
odoo_scaffolder/icons/Inventory & Procurment.png
odoo_scaffolder/icons/Manufacturing.png
odoo_scaffolder/icons/POS.png
odoo_scaffolder/icons/README.md
odoo_scaffolder/icons/Sales.png
odoo_scaffolder/icons/Services.png
odoo_scaffolder/icons/Website.png
odoo_scaffolder-0.1.1.dist-info/licenses/LICENSE
odoo_scaffolder-0.1.1.dist-info/METADATA
odoo_scaffolder-0.1.1.dist-info/WHEEL
odoo_scaffolder-0.1.1.dist-info/entry_points.txt
odoo_scaffolder-0.1.1.dist-info/top_level.txt
odoo_scaffolder-0.1.1.dist-info/RECORD
