Metadata-Version: 2.4
Name: odoo-scaffolder
Version: 0.1.1
Summary: A modern scaffolding tool for creating Odoo modules with best practices
Author-email: Ammar Abu Zahra <ammarya12@gmail.com>
License: MIT
Project-URL: Homepage, https://github.com/a-abuzahra/odoo-scaffolder
Project-URL: Repository, https://github.com/a-abuzahra/odoo-scaffolder
Project-URL: Issues, https://github.com/a-abuzahra/odoo-scaffolder/issues
Keywords: odoo,scaffold,module,generator,cli
Classifier: Development Status :: 4 - Beta
Classifier: Intended Audience :: Developers
Classifier: License :: OSI Approved :: MIT License
Classifier: Operating System :: OS Independent
Classifier: Programming Language :: Python :: 3
Classifier: Programming Language :: Python :: 3.7
Classifier: Programming Language :: Python :: 3.8
Classifier: Programming Language :: Python :: 3.9
Classifier: Programming Language :: Python :: 3.10
Classifier: Programming Language :: Python :: 3.11
Classifier: Programming Language :: Python :: 3.12
Classifier: Topic :: Software Development :: Code Generators
Classifier: Topic :: Software Development :: Libraries :: Python Modules
Requires-Python: >=3.7
License-File: LICENSE
Dynamic: license-file
